Proyecto 1/TriS16bits.v
//////////////////////////////////////////////////////////////////////////////////////////////////////
//
// TriS16bits.v
// 
// Este modulo sirve como triestado de 16 bits
//
//////////////////////////////////////////////////////////////////////////////////////////////////////


module TriS16bits (
    input [15:0] IN,
    input SEL, 
    output wire [15:0] OUT
);

assign OUT = SEL ? IN : 16'bz;
    
endmodule


//varios registros pueden compartir una línea de bus, pero solo uno debe conducir 
//en un momento dado. Usar Z (alta impedancia) permite que un módulo "se desconecte" del bus cuando no le toca transmitir.

Proyecto 1/Mux16x1.v
//////////////////////////////////////////////////////////////////////////////////////////////////////
//
// Mux16x1.v
//
// Este modulo sirve como Mux16x1 de salida
//
//////////////////////////////////////////////////////////////////////////////////////////////////////

module Mux16x1 (
    input [15:0] A0, 
    input [15:0] A1, 
    input [15:0] A2, 
    input [15:0] A3,
    input [15:0] A4,
    input [15:0] A5,
    input [15:0] A6,
    input [15:0] A7,
    input [15:0] A8,
    input [15:0] A9,
    input [15:0] A10,
    input [15:0] A11,
    input [15:0] A12,
    input [15:0] A13,
    input [15:0] A14,
    input [15:0] A15,
    input [3:0] SEL,
    output reg [15:0] OUT
);

always @(*) begin
    case (SEL)
        4'b0000 : OUT = A0;  //AL 
        4'b0001 : OUT = A1;  //CL 
        4'b0010 : OUT = A2;  //DL 
        4'b0011 : OUT = A3;  //BL 
        4'b0100 : OUT = A4;  //AH 
        4'b0101 : OUT = A5;  //CH 
        4'b0110 : OUT = A6;  //DH 
        4'b0111 : OUT = A7;  //BH 
        4'b1000 : OUT = A8;  //AX 
        4'b1001 : OUT = A9;  //CX 
        4'b1010 : OUT = A10; //DX 
        4'b1011 : OUT = A11; //BX 
        4'b1100 : OUT = A12; //SP 
        4'b1101 : OUT = A13; //BP 
        4'b1110 : OUT = A14; //SI 
        4'b1111 : OUT = A15; //DI 
    endcase
end

endmodule

Proyecto 1/Reg16bits.v
//////////////////////////////////////////////////////////////////////////////////////////////////////
//
// Reg16bits.v
// 
// Este modulo sirve como para crear los registros de 16 bits
//
//////////////////////////////////////////////////////////////////////////////////////////////////////

module Reg16bits (
    input CLK, 
    input RST, 
    input WriteEnable,
    input [15:0] D,
    output reg [15:0] Q 
);
 
always @(posedge CLK or posedge RST) begin
    if (RST)
        Q = 16'b0;
    else if (WriteEnable)
        Q = D; 
    else 
        Q = Q;
end


endmodule

Proyecto 1/Reg8bits.v
//////////////////////////////////////////////////////////////////////////////////////////////////////
//
// Reg8bits.v
// 
// Este modulo sirve como registros de 8 bits
//
//////////////////////////////////////////////////////////////////////////////////////////////////////

module Reg8bits (
    input CLK, 
    input RST, 
    input WriteEnable,
    input [7:0] D,
    output reg [7:0] Q 
);
    

always @(posedge CLK or posedge RST) begin
    if (RST)
        Q = 8'b0;
    else if (WriteEnable)
        Q = D;
    else 
        Q = Q;
end

endmodule

Proyecto 1/Mux2x8.v
//////////////////////////////////////////////////////////////////////////////////////////////////////
//
// Mux2x8.v
// 
// Este modulo sirve como Mux2x8
//
//////////////////////////////////////////////////////////////////////////////////////////////////////

module Mux2x8 (
    input [7:0] ENT1,
    input [7:0] ENT2,
    input SEL_H_L,
    output reg [7:0] OUT
);

always @(*) begin
    case (SEL_H_L)
        1'b0 : OUT = ENT1;
        1'b1 : OUT = ENT2; 
    endcase
end

endmodule

Proyecto 1/Registros.v
//////////////////////////////////////////////////////////////////////////////////////////////////////
//
// Registros.v
// 
// Este modulo sirve como modulo para "crear" los registros
//
//////////////////////////////////////////////////////////////////////////////////////////////////////


module Registros (
    input CLK, 
    input RST, 
    input SEL,  
    input SEL_H_L,            
    input [15:0] DATA, 
    input [11:0] WE,

    output wire [7:0] AL, 
    output wire [7:0] CL, 
    output wire [7:0] DL, 
    output wire [7:0] BL, 
    output wire [7:0] AH, 
    output wire [7:0] CH, 
    output wire [7:0] DH, 
    output wire [7:0] BH,

    output wire [15:0] SP,  
    output wire [15:0] BP,
    output wire [15:0] SI,
    output wire [15:0] DI 
);

    
//Llamada al mux para selecionar High o Low en los registros de 8 bits
wire [7:0] Temp;
Mux2x8 mux2x8 (DATA[7:0], DATA [15:8], SEL_H_L, Temp);

//Llamada a Reg8bits para "crear" los registros de 8 bits
Reg8bits RegAL (CLK, RST, WE[11], DATA[7:0], AL); 
Reg8bits RegCL (CLK, RST, WE[10], DATA[7:0], CL); 
Reg8bits RegDL (CLK, RST, WE[9], DATA[7:0], DL); 
Reg8bits RegBL (CLK, RST, WE[8], DATA[7:0], BL); 
Reg8bits RegAH (CLK, RST, WE[7], Temp, AH); 
Reg8bits RegCH (CLK, RST, WE[6], Temp, CH); 
Reg8bits RegDH (CLK, RST, WE[5], Temp, DH); 
Reg8bits RegBH (CLK, RST, WE[4], Temp, BH); 

//Llamada a Reg16bits para "crear" los registros de 16 bits

Reg16bits RegSP (CLK, RST, WE[3], DATA, SP); 
Reg16bits RegBP (CLK, RST, WE[2], DATA, BP); 
Reg16bits RegSI (CLK, RST, WE[1], DATA, SI); 
Reg16bits RegDI (CLK, RST, WE[0], DATA, DI); 

endmodule

Proyecto 1/Deco.v
//////////////////////////////////////////////////////////////////////////////////////////////////////
//
// Deco.v
// 
// Este modulo sirve como Decodificador 
//
//////////////////////////////////////////////////////////////////////////////////////////////////////


module Deco (
    input WR,
    input [3:0] SEL, 
    output reg [11:0] WE
);
    
    always @(*) begin
        case ({WR, SEL})
            5'b10000 : WE = 12'b100000000000; //AL 
            5'b10001 : WE = 12'b010000000000; //CL
            5'b10010 : WE = 12'b001000000000; //DL
            5'b10011 : WE = 12'b001000000000; //BL
            5'b10100 : WE = 12'b000010000000; //AH
            5'b10101 : WE = 12'b000001000000; //CH
            5'b10110 : WE = 12'b100000100000; //DH
            5'b10111 : WE = 12'b100000010000; //BH
            5'b11000 : WE = 12'b100010000000; //AX
            5'b11001 : WE = 12'b010001000000; //CX
            5'b11010 : WE = 12'b001000100000; //DX
            5'b11011 : WE = 12'b000100010000; //BX
            5'b11100 : WE = 12'b000000001000; //SP
            5'b11101 : WE = 12'b000000000100; //BP
            5'b11110 : WE = 12'b000000000010; //SI
            5'b11111 : WE = 12'b000000000001; //DI

            default : WE = 12'b000000000000;  
        endcase
    end
endmodule

Proyecto 1/Top.v
//////////////////////////////////////////////////////////////////////////////////////////////////////
//
// Top.v
// 
// Este modulo sirve como Top para el banco de registros del 8088
//
//////////////////////////////////////////////////////////////////////////////////////////////////////

`include "Registros.v"
`include "Deco.v"
`include "Mux2x8.v"
`include "Mux16x1.v"
`include "Reg8bits.v"
`include "Reg16bits.v"
`include "TriS16bits.v"


module BancoDeRegistros8088 (
    input CLK, 
    input RST, 
    input RD, 
    input WR, 
    input [3:0] SEL, 
    inout wire [15:0] DATA
);

//Llamada al deco de escritura 
wire [11:0] WE;
Deco DecoEscritura (WR, SEL, WE);

wire SEL_H_L;
assign SEL_H_L = (
    SEL == 4'b0100 || SEL == 4'b0101 || SEL == 4'b0110 || SEL == 4'b0111 || // AH, CH, DH, BH
    SEL == 4'b1000 || SEL == 4'b1001 || SEL == 4'b1010 || SEL == 4'b1011    // AX, CX, DX, BX
);

//Llamada a Registros
wire [7:0] AL, CL, DL, BL, AH, CH, DH, BH;
wire [15:0] SP, BP, SI, DI;
Registros Regs (CLK, RST, SEL[3], SEL_H_L, DATA, WE, AL, CL, DL, BL, AH, CH, DH, BH, SP, BP, SI, DI);

//Llamada a mux16x1
wire [15:0] SALIDA;
Mux16x1 MuxSalida (
    {8'b0, AL},
    {8'b0, CL},
    {8'b0, DL},
    {8'b0, BL},
    {8'b0, AH},
    {8'b0, CH},
    {8'b0, DH},
    {8'b0, BH},
    {AH, AL},
    {CH, CL},
    {DH, DL},
    {BH, BL},
    SP, 
    BP, 
    SI, 
    DI,
    SEL, 
    SALIDA);


//Llamada al tri estado
    TriS16bits TriEstado (SALIDA, RD, DATA); 
    
endmodule

Proyecto 1/Top_tb.sv
//////////////////////////////////////////////////////////////////////////////////////////////////////
//
// Top_tb.v
// 
// Este modulo sirve como testbench del modulo top
//
//////////////////////////////////////////////////////////////////////////////////////////////////////


`timescale 1ns/1ns
`include "Top.v"

module BancoDeRegistros8088_tb ();

//Declaración de señales del testbench
reg CLK;
reg RST;
reg RD;
reg WR;
reg [3:0] SEL;


// Señales para controlar el bus inout
reg [15:0] DATA_drive;
reg DATA_en;
wire [15:0] DATA;

// Simulación del comportamiento triestado del bus
assign DATA = DATA_en ? DATA_drive : 16'bz;

//Instanciación del modulo BancoDeRegistros8088
BancoDeRegistros8088 DUT(
    .CLK(CLK),
    .RST(RST),
    .RD(RD),
    .WR(WR),
    .SEL(SEL),
    .DATA(DATA)
);


//creacion del reloj
initial begin
    CLK = 0;
    forever #10 CLK =~ CLK;
end



initial begin

    $dumpfile("Top_tb.vcd");
    $dumpvars(0, BancoDeRegistros8088_tb);


    // Reset inicial
    RST = 1; WR = 0; RD = 0; SEL = 0;
    DATA_drive = 16'h0000;
    DATA_en = 0;
    #20 
    RST = 0;



//inicio de pruebas
    #50

///////////////////////////////////////////////////////////////////
 //Escritura y lectura en AL

    //escritura en registro AL (SEL = 4'b0000)
    SEL = 4'b0000;
    DATA_drive = 16'h00A1; //Dato a escribir
    DATA_en = 1;          //Conducir al bus
    WR = 1;


    #20;


    WR = 0;
    DATA_en = 0;          //Soltar el bus


    //Lectura desde AL
    #20;
    SEL = 4'b0000;
    RD = 1;
    #20;
    $display("Lectura desde AL: %h", DATA);
    RD = 0;
///////////////////////////////////////////////////////////////////




///////////////////////////////////////////////////////////////////
 //Escritura y lectura en AH

    #20;
    //escritura en registro AH (SEL = 4'b0100)
    SEL = 4'b0100; //AH
    DATA_drive = 16'hA200; //Solo byte alto
    DATA_en = 1;           //Conducir al bus
    WR = 1;


    #20;


    WR = 0;
    DATA_en = 0;        //Soltar el bus


    // Lectura desde AH
    #20;
    SEL = 4'b0100;
    RD = 1;
    #20;
    $display("Lectura desde AH: %h", DATA);
    RD = 0;
///////////////////////////////////////////////////////////////////


///////////////////////////////////////////////////////////////////
// Escritura y lectura en CL

    #20;

    //escritura en registro CL (SEL = 4'b0001)     
    SEL = 4'b0001; // CL
    DATA_drive = 16'h00C1; //Solo byte bajo
    DATA_en = 1; //Conducir al bus
    WR = 1;


    #20;


    WR = 0;
    DATA_en = 0; //Soltar el bus

   // Lectura desde CL
    #20;
    SEL = 4'b0001;
    RD = 1;
    #20;
    $display("Lectura desde CL: %h", DATA);
    RD = 0;
///////////////////////////////////////////////////////////////////

///////////////////////////////////////////////////////////////////
// Escritura y lectura en CH

    #20;

    //escritura en registro CH (SEL = 4'b0101)
    SEL = 4'b0101; // CH
    DATA_drive = 16'hC200; //Solo byte alto
    DATA_en = 1; //Conducir al bus
    WR = 1;

    
    #20;
    
    
    WR = 0;
    DATA_en = 0; //Soltar el bus

  // Lectura desde CH
    #20;
    SEL = 4'b0101;
    RD = 1;
    #20;
    $display("Lectura desde CH: %h", DATA);
    RD = 0;
///////////////////////////////////////////////////////////////////



///////////////////////////////////////////////////////////////////
// Escritura y lectura en DL

    #20;

    //escritura en registro DL (SEL = 4'b0010)    
    SEL = 4'b0010; // DL
    DATA_drive = 16'h00D1; //Solo byte bajo
    DATA_en = 1; //Conducir al bus
    WR = 1;


    #20;
    
    
    WR = 0;
    DATA_en = 0; //Soltar el bus

   // Lectura desde DL
    #20;
    SEL = 4'b0010;
    RD = 1;
    #20;
    $display("Lectura desde DL: %h", DATA);
    RD = 0;
///////////////////////////////////////////////////////////////////

///////////////////////////////////////////////////////////////////
// Escritura y lectura en DH

    #20;

    //escritura en registro DH (SEL = 4'b0110)
    SEL = 4'b0110; // DH
    DATA_drive = 16'hD200; //Solo byte alto
    DATA_en = 1; //Conducir al bus
    WR = 1;


    #20;
    
    
    WR = 0;
    DATA_en = 0; //Soltar el bus

   // Lectura desde DH
    #20;
    SEL = 4'b0110;
    RD = 1;
    #20;
    $display("Lectura desde DH: %h", DATA);
    RD = 0;
///////////////////////////////////////////////////////////////////



///////////////////////////////////////////////////////////////////
// Escritura y lectura en BL

    #20;

    //escritura en registro BL (SEL = 4'b0011)
    SEL = 4'b0011; // BL
    DATA_drive = 16'h00B1; //Solo byte bajo
    DATA_en = 1; //Conducir al bus
    WR = 1;
    
    
    #20;
    
    
    WR = 0;
    DATA_en = 0; //Soltar el bus

   // Lectura desde BL
    #20;
    SEL = 4'b0011;
    RD = 1;
    #20;
    $display("Lectura desde BL: %h", DATA);
    RD = 0;
///////////////////////////////////////////////////////////////////

///////////////////////////////////////////////////////////////////
// Escritura y lectura en BH

    #20;

    //escritura en registro BH (SEL = 4'b0111)
    SEL = 4'b0111; // BH
    DATA_drive = 16'hB200; //Solo byte alto
    DATA_en = 1; //Conducir al bus
    WR = 1;

    
    #20;
    
    
    WR = 0;
    DATA_en = 0; //Soltar el bus

   // Lectura desde BH
    #20;
    SEL = 4'b0111;
    RD = 1;
    #20;
    $display("Lectura desde BH: %h", DATA);
    RD = 0;
///////////////////////////////////////////////////////////////////


///////////////////////////////////////////////////////////////////
// Escritura y lectura en AX

    #20;

    //escritura en registro BX (SEL = 4'b1000)
    SEL = 4'b1000;        // AX
    DATA_drive = 16'hA3A4; //Ambos, byte alto y bajo
    DATA_en = 1; //Conducir al bus
    WR = 1;
    
    
    #20;
    
    
    WR = 0;
    DATA_en = 0; //Soltar el bus

    // Lectura desde AX
    #20;
    SEL = 4'b1000;
    RD = 1;
    #20;
    $display("Lectura desde AX: %h", DATA);
    RD = 0;
///////////////////////////////////////////////////////////////////



///////////////////////////////////////////////////////////////////
// Escritura y lectura en CX

    #20;

    //escritura en registro BX (SEL = 4'b1001)
    SEL = 4'b1001;        // CX
    DATA_drive = 16'hC3C4; //Ambos, byte alto y bajo
    DATA_en = 1; //Conducir al bus
    WR = 1;


    #20;


    WR = 0;
    DATA_en = 0; //Soltar el bus


    // Lectura desde CX
    #20;
    SEL = 4'b1001;
    RD = 1;
    #20;
    $display("Lectura desde CX: %h", DATA);
    RD = 0;
///////////////////////////////////////////////////////////////////



///////////////////////////////////////////////////////////////////
// Escritura y lectura en DX

    #20;

    //escritura en registro DX (SEL = 4'b1010)
    SEL = 4'b1010;        // DX
    DATA_drive = 16'hD3D4; //Ambos, byte alto y bajo
    DATA_en = 1; //Conducir al bus
    WR = 1;


    #20;
    
    
    WR = 0;
    DATA_en = 0; //Soltar el bus


    // Lectura desde DX
    #20;
    SEL = 4'b1010;
    RD = 1;
    #20;
    $display("Lectura desde DX: %h", DATA);
    RD = 0;
///////////////////////////////////////////////////////////////////


///////////////////////////////////////////////////////////////////
// Escritura y lectura en BX

    #20;
    
    //escritura en registro BX (SEL = 4'b1011)
    SEL = 4'b1011;        // BX
    DATA_drive = 16'hB3B4; //Ambos, byte alto y bajo
    DATA_en = 1; //Conducir al bus
    WR = 1;


    #20;


    WR = 0;
    DATA_en = 0; //Soltar el bus


    // Lectura desde BX
    #20;
    SEL = 4'b1011;
    RD = 1;
    #20;
    $display("Lectura desde BX: %h", DATA);
    RD = 0;
///////////////////////////////////////////////////////////////////



///////////////////////////////////////////////////////////////////
// Escritura y lectura en SP

    #20;
    //escritura en registro SP (SEL = 4'b1100)
    SEL = 4'b1100;        // SP
    DATA_drive = 16'h1234;
    DATA_en = 1; //Conducir al bus
    WR = 1;


    #30;


    WR = 0;
    DATA_en = 0;//Soltar el bus


    // Lectura desde SP
    #20;
    SEL = 4'b1100;
    RD = 1;
    #20;
    $display("Lectura desde SP: %h", DATA);
    RD = 0;
    #50
///////////////////////////////////////////////////////////////////

///////////////////////////////////////////////////////////////////
// Escritura y lectura en BP

    #20;
    //escritura en registro BP (SEL = 4'b1101)
    SEL = 4'b1101;        // BP
    WR = 1;
    DATA_drive = 16'h2345;
    DATA_en = 1; //Conducir al bus



    #30;


    WR = 0;
    DATA_en = 0;//Soltar el bus


    // Lectura desde BP
    #20;
    SEL = 4'b1101;
    RD = 1;
    #20;
    $display("Lectura desde BP: %h", DATA);
    RD = 0;
    #50
///////////////////////////////////////////////////////////////////

///////////////////////////////////////////////////////////////////
// Escritura y lectura en SI

    #20;
    //escritura en registro SI (SEL = 4'b1110)
    SEL = 4'b1110;        // SI
    WR = 1;
    DATA_drive = 16'h3456;
    DATA_en = 1; //Conducir al bus



    #30;


    WR = 0;
    DATA_en = 0;//Soltar el bus


    // Lectura desde SI
    #20;
    SEL = 4'b1110;
    RD = 1;
    #20;
    $display("Lectura desde SI: %h", DATA);
    RD = 0;
    #50
///////////////////////////////////////////////////////////////////

///////////////////////////////////////////////////////////////////
// Escritura y lectura en DI

    #20;
    //escritura en registro DI (SEL = 4'b1111)
    SEL = 4'b1111;        // DI
    WR = 1;
    DATA_drive = 16'h4567;
    DATA_en = 1; //Conducir al bus



    #30;


    WR = 0;
    DATA_en = 0;//Soltar el bus


    // Lectura desde DI
    #20;
    SEL = 4'b1111;
    RD = 1;
    #20;
    $display("Lectura desde DI: %h", DATA);
    RD = 0;
    #50
///////////////////////////////////////////////////////////////////


    $display("Test completado");
    $finish;

end

endmodule

Proyecto 1/Top_tb.vcd
$date
	Thu Apr 17 16:58:46 2025
$end
$version
	Icarus Verilog
$end
$timescale
	1ns
$end
$scope module BancoDeRegistros8088_tb $end
$var wire 16 ! DATA [15:0] $end
$var reg 1 " CLK $end
$var reg 16 # DATA_drive [15:0] $end
$var reg 1 $ DATA_en $end
$var reg 1 % RD $end
$var reg 1 & RST $end
$var reg 4 ' SEL [3:0] $end
$var reg 1 ( WR $end
$scope module DUT $end
$var wire 1 " CLK $end
$var wire 16 ) DATA [15:0] $end
$var wire 1 % RD $end
$var wire 1 & RST $end
$var wire 4 * SEL [3:0] $end
$var wire 1 + SEL_H_L $end
$var wire 1 ( WR $end
$var wire 12 , WE [11:0] $end
$var wire 16 - SP [15:0] $end
$var wire 16 . SI [15:0] $end
$var wire 16 / SALIDA [15:0] $end
$var wire 8 0 DL [7:0] $end
$var wire 16 1 DI [15:0] $end
$var wire 8 2 DH [7:0] $end
$var wire 8 3 CL [7:0] $end
$var wire 8 4 CH [7:0] $end
$var wire 16 5 BP [15:0] $end
$var wire 8 6 BL [7:0] $end
$var wire 8 7 BH [7:0] $end
$var wire 8 8 AL [7:0] $end
$var wire 8 9 AH [7:0] $end
$scope module DecoEscritura $end
$var wire 4 : SEL [3:0] $end
$var wire 1 ( WR $end
$var reg 12 ; WE [11:0] $end
$upscope $end
$scope module MuxSalida $end
$var wire 16 < A0 [15:0] $end
$var wire 16 = A1 [15:0] $end
$var wire 16 > A10 [15:0] $end
$var wire 16 ? A11 [15:0] $end
$var wire 16 @ A2 [15:0] $end
$var wire 16 A A3 [15:0] $end
$var wire 16 B A4 [15:0] $end
$var wire 16 C A5 [15:0] $end
$var wire 16 D A6 [15:0] $end
$var wire 16 E A7 [15:0] $end
$var wire 16 F A8 [15:0] $end
$var wire 16 G A9 [15:0] $end
$var wire 4 H SEL [3:0] $end
$var wire 16 I A15 [15:0] $end
$var wire 16 J A14 [15:0] $end
$var wire 16 K A13 [15:0] $end
$var wire 16 L A12 [15:0] $end
$var reg 16 M OUT [15:0] $end
$upscope $end
$scope module Regs $end
$var wire 1 " CLK $end
$var wire 16 N DATA [15:0] $end
$var wire 1 & RST $end
$var wire 1 O SEL $end
$var wire 1 + SEL_H_L $end
$var wire 12 P WE [11:0] $end
$var wire 8 Q Temp [7:0] $end
$var wire 16 R SP [15:0] $end
$var wire 16 S SI [15:0] $end
$var wire 8 T DL [7:0] $end
$var wire 16 U DI [15:0] $end
$var wire 8 V DH [7:0] $end
$var wire 8 W CL [7:0] $end
$var wire 8 X CH [7:0] $end
$var wire 16 Y BP [15:0] $end
$var wire 8 Z BL [7:0] $end
$var wire 8 [ BH [7:0] $end
$var wire 8 \ AL [7:0] $end
$var wire 8 ] AH [7:0] $end
$scope module RegAH $end
$var wire 1 " CLK $end
$var wire 1 & RST $end
$var wire 1 ^ WriteEnable $end
$var wire 8 _ D [7:0] $end
$var reg 8 ` Q [7:0] $end
$upscope $end
$scope module RegAL $end
$var wire 1 " CLK $end
$var wire 8 a D [7:0] $end
$var wire 1 & RST $end
$var wire 1 b WriteEnable $end
$var reg 8 c Q [7:0] $end
$upscope $end
$scope module RegBH $end
$var wire 1 " CLK $end
$var wire 1 & RST $end
$var wire 1 d WriteEnable $end
$var wire 8 e D [7:0] $end
$var reg 8 f Q [7:0] $end
$upscope $end
$scope module RegBL $end
$var wire 1 " CLK $end
$var wire 8 g D [7:0] $end
$var wire 1 & RST $end
$var wire 1 h WriteEnable $end
$var reg 8 i Q [7:0] $end
$upscope $end
$scope module RegBP $end
$var wire 1 " CLK $end
$var wire 16 j D [15:0] $end
$var wire 1 & RST $end
$var wire 1 k WriteEnable $end
$var reg 16 l Q [15:0] $end
$upscope $end
$scope module RegCH $end
$var wire 1 " CLK $end
$var wire 1 & RST $end
$var wire 1 m WriteEnable $end
$var wire 8 n D [7:0] $end
$var reg 8 o Q [7:0] $end
$upscope $end
$scope module RegCL $end
$var wire 1 " CLK $end
$var wire 8 p D [7:0] $end
$var wire 1 & RST $end
$var wire 1 q WriteEnable $end
$var reg 8 r Q [7:0] $end
$upscope $end
$scope module RegDH $end
$var wire 1 " CLK $end
$var wire 1 & RST $end
$var wire 1 s WriteEnable $end
$var wire 8 t D [7:0] $end
$var reg 8 u Q [7:0] $end
$upscope $end
$scope module RegDI $end
$var wire 1 " CLK $end
$var wire 16 v D [15:0] $end
$var wire 1 & RST $end
$var wire 1 w WriteEnable $end
$var reg 16 x Q [15:0] $end
$upscope $end
$scope module RegDL $end
$var wire 1 " CLK $end
$var wire 8 y D [7:0] $end
$var wire 1 & RST $end
$var wire 1 z WriteEnable $end
$var reg 8 { Q [7:0] $end
$upscope $end
$scope module RegSI $end
$var wire 1 " CLK $end
$var wire 16 | D [15:0] $end
$var wire 1 & RST $end
$var wire 1 } WriteEnable $end
$var reg 16 ~ Q [15:0] $end
$upscope $end
$scope module RegSP $end
$var wire 1 " CLK $end
$var wire 16 !" D [15:0] $end
$var wire 1 & RST $end
$var wire 1 "" WriteEnable $end
$var reg 16 #" Q [15:0] $end
$upscope $end
$scope module mux2x8 $end
$var wire 8 $" ENT1 [7:0] $end
$var wire 8 %" ENT2 [7:0] $end
$var wire 1 + SEL_H_L $end
$var reg 8 &" OUT [7:0] $end
$upscope $end
$upscope $end
$scope module TriEstado $end
$var wire 16 '" IN [15:0] $end
$var wire 16 (" OUT [15:0] $end
$var wire 1 % SEL $end
$upscope $end
$upscope $end
$upscope $end
$enddefinitions $end
$comment Show the parameter values. $end
$dumpall
$end
#0
$dumpvars
bz ("
b0 '"
bz &"
bz %"
bz $"
b0 #"
0""
bz !"
b0 ~
0}
bz |
b0 {
0z
bz y
b0 x
0w
bz v
b0 u
bz t
0s
b0 r
0q
bz p
b0 o
bz n
0m
b0 l
0k
bz j
b0 i
0h
bz g
b0 f
bz e
0d
b0 c
0b
bz a
b0 `
bz _
0^
b0 ]
b0 \
b0 [
b0 Z
b0 Y
b0 X
b0 W
b0 V
b0 U
b0 T
b0 S
b0 R
bz Q
b0 P
0O
bz N
b0 M
b0 L
b0 K
b0 J
b0 I
b0 H
b0 G
b0 F
b0 E
b0 D
b0 C
b0 B
b0 A
b0 @
b0 ?
b0 >
b0 =
b0 <
b0 ;
b0 :
b0 9
b0 8
b0 7
b0 6
b0 5
b0 4
b0 3
b0 2
b0 1
b0 0
b0 /
b0 .
b0 -
b0 ,
0+
b0 *
bz )
0(
b0 '
1&
0%
0$
b0 #
0"
bz !
$end
#10
1"
#20
0"
0&
#30
1"
#40
0"
#50
1"
#60
0"
#70
b10100001 Q
b10100001 _
b10100001 e
b10100001 n
b10100001 t
b10100001 &"
1b
b10100001 $"
b0 %"
b10100001 a
b10100001 p
b10100001 y
b10100001 g
b100000000000 ,
b100000000000 ;
b100000000000 P
b10100001 !
b10100001 )
b10100001 N
b10100001 j
b10100001 v
b10100001 |
b10100001 !"
b10100001 ("
1"
1(
1$
b10100001 #
#80
0"
#90
bz Q
bz _
bz e
bz n
bz t
bz &"
b10100001 /
b10100001 M
b10100001 '"
bz $"
bz %"
bz a
bz p
bz y
bz g
0b
b10100001 F
b10100001 <
b10100001 8
b10100001 \
b10100001 c
bz !
bz )
bz N
bz j
bz v
bz |
bz !"
bz ("
b0 ,
b0 ;
b0 P
1"
0$
0(
#100
0"
#110
b10100001 Q
b10100001 _
b10100001 e
b10100001 n
b10100001 t
b10100001 &"
b10100001 $"
b0 %"
b10100001 a
b10100001 p
b10100001 y
b10100001 g
b10100001 !
b10100001 )
b10100001 N
b10100001 j
b10100001 v
b10100001 |
b10100001 !"
b10100001 ("
1"
1%
#120
0"
#130
bz Q
bz _
bz e
bz n
bz t
bz &"
bz $"
bz %"
bz a
bz p
bz y
bz g
bz !
bz )
bz N
bz j
bz v
bz |
bz !"
bz ("
1"
0%
#140
0"
#150
1+
b10100010 Q
b10100010 _
b10100010 e
b10100010 n
b10100010 t
b10100010 &"
b0 $"
b10100010 %"
b0 a
b0 p
b0 y
b0 g
1^
b1010001000000000 !
b1010001000000000 )
b1010001000000000 N
b1010001000000000 j
b1010001000000000 v
b1010001000000000 |
b1010001000000000 !"
b1010001000000000 ("
b10000000 ,
b10000000 ;
b10000000 P
b0 /
b0 M
b0 '"
1"
1(
1$
b1010001000000000 #
b100 '
b100 *
b100 :
b100 H
#160
0"
#170
bz Q
bz _
bz e
bz n
bz t
bz &"
b10100010 /
b10100010 M
b10100010 '"
bz $"
bz %"
bz a
bz p
bz y
bz g
0^
b1010001010100001 F
b10100010 B
b10100010 9
b10100010 ]
b10100010 `
bz !
bz )
bz N
bz j
bz v
bz |
bz !"
bz ("
b0 ,
b0 ;
b0 P
1"
0$
0(
#180
0"
#190
b0 Q
b0 _
b0 e
b0 n
b0 t
b0 &"
b10100010 $"
b0 %"
b10100010 a
b10100010 p
b10100010 y
b10100010 g
b10100010 !
b10100010 )
b10100010 N
b10100010 j
b10100010 v
b10100010 |
b10100010 !"
b10100010 ("
1"
1%
#200
0"
#210
bz Q
bz _
bz e
bz n
bz t
bz &"
bz $"
bz %"
bz a
bz p
bz y
bz g
bz !
bz )
bz N
bz j
bz v
bz |
bz !"
bz ("
1"
0%
#220
0"
#230
0+
b11000001 Q
b11000001 _
b11000001 e
b11000001 n
b11000001 t
b11000001 &"
b11000001 $"
b0 %"
b11000001 a
b11000001 p
b11000001 y
b11000001 g
1q
b11000001 !
b11000001 )
b11000001 N
b11000001 j
b11000001 v
b11000001 |
b11000001 !"
b11000001 ("
b10000000000 ,
b10000000000 ;
b10000000000 P
b0 /
b0 M
b0 '"
1"
1(
1$
b11000001 #
b1 '
b1 *
b1 :
b1 H
#240
0"
#250
bz Q
bz _
bz e
bz n
bz t
bz &"
b11000001 /
b11000001 M
b11000001 '"
bz $"
bz %"
bz a
bz p
bz y
bz g
0q
b11000001 G
b11000001 =
b11000001 3
b11000001 W
b11000001 r
bz !
bz )
bz N
bz j
bz v
bz |
bz !"
bz ("
b0 ,
b0 ;
b0 P
1"
0$
0(
#260
0"
#270
b11000001 Q
b11000001 _
b11000001 e
b11000001 n
b11000001 t
b11000001 &"
b11000001 $"
b0 %"
b11000001 a
b11000001 p
b11000001 y
b11000001 g
b11000001 !
b11000001 )
b11000001 N
b11000001 j
b11000001 v
b11000001 |
b11000001 !"
b11000001 ("
1"
1%
#280
0"
#290
bz Q
bz _
bz e
bz n
bz t
bz &"
bz $"
bz %"
bz a
bz p
bz y
bz g
bz !
bz )
bz N
bz j
bz v
bz |
bz !"
bz ("
1"
0%
#300
0"
#310
1+
b11000010 Q
b11000010 _
b11000010 e
b11000010 n
b11000010 t
b11000010 &"
b0 $"
b11000010 %"
b0 a
b0 p
b0 y
b0 g
1m
b1100001000000000 !
b1100001000000000 )
b1100001000000000 N
b1100001000000000 j
b1100001000000000 v
b1100001000000000 |
b1100001000000000 !"
b1100001000000000 ("
b1000000 ,
b1000000 ;
b1000000 P
b0 /
b0 M
b0 '"
1"
1(
1$
b1100001000000000 #
b101 '
b101 *
b101 :
b101 H
#320
0"
#330
bz Q
bz _
bz e
bz n
bz t
bz &"
b11000010 /
b11000010 M
b11000010 '"
bz $"
bz %"
bz a
bz p
bz y
bz g
0m
b1100001011000001 G
b11000010 C
b11000010 4
b11000010 X
b11000010 o
bz !
bz )
bz N
bz j
bz v
bz |
bz !"
bz ("
b0 ,
b0 ;
b0 P
1"
0$
0(
#340
0"
#350
b0 Q
b0 _
b0 e
b0 n
b0 t
b0 &"
b11000010 $"
b0 %"
b11000010 a
b11000010 p
b11000010 y
b11000010 g
b11000010 !
b11000010 )
b11000010 N
b11000010 j
b11000010 v
b11000010 |
b11000010 !"
b11000010 ("
1"
1%
#360
0"
#370
bz Q
bz _
bz e
bz n
bz t
bz &"
bz $"
bz %"
bz a
bz p
bz y
bz g
bz !
bz )
bz N
bz j
bz v
bz |
bz !"
bz ("
1"
0%
#380
0"
#390
0+
b11010001 Q
b11010001 _
b11010001 e
b11010001 n
b11010001 t
b11010001 &"
b11010001 $"
b0 %"
b11010001 a
b11010001 p
b11010001 y
b11010001 g
1z
b11010001 !
b11010001 )
b11010001 N
b11010001 j
b11010001 v
b11010001 |
b11010001 !"
b11010001 ("
b1000000000 ,
b1000000000 ;
b1000000000 P
b0 /
b0 M
b0 '"
1"
1(
1$
b11010001 #
b10 '
b10 *
b10 :
b10 H
#400
0"
