Proyecto 1/TriS16bits.v
//////////////////////////////////////////////////////////////////////////////////////////////////////
//
// TriS16bits.v
// 
// Este modulo sirve como triestado de 16 bits
//
//////////////////////////////////////////////////////////////////////////////////////////////////////


module TriS16bits (
    input [15:0] IN,
    input SEL, 
    output wire [15:0] OUT
);

assign OUT = SEL ? IN : 16'bz;
    
endmodule


//varios registros pueden compartir una línea de bus, pero solo uno debe conducir 
//en un momento dado. Usar Z (alta impedancia) permite que un módulo "se desconecte" del bus cuando no le toca transmitir.

Proyecto 1/Mux16x1.v
//////////////////////////////////////////////////////////////////////////////////////////////////////
//
// Mux16x1.v
//
// Este modulo sirve como Mux16x1 de salida
//
//////////////////////////////////////////////////////////////////////////////////////////////////////

module Mux16x1 (
    input [15:0] A0, 
    input [15:0] A1, 
    input [15:0] A2, 
    input [15:0] A3,
    input [15:0] A4,
    input [15:0] A5,
    input [15:0] A6,
    input [15:0] A7,
    input [15:0] A8,
    input [15:0] A9,
    input [15:0] A10,
    input [15:0] A11,
    input [15:0] A12,
    input [15:0] A13,
    input [15:0] A14,
    input [15:0] A15,
    input [3:0] SEL,
    output reg [15:0] OUT
);

always @(*) begin
    case (SEL)
        4'b0000 : OUT = A0;  //AL 
        4'b0001 : OUT = A1;  //CL 
        4'b0010 : OUT = A2;  //DL 
        4'b0011 : OUT = A3;  //BL 
        4'b0100 : OUT = A4;  //AH 
        4'b0101 : OUT = A5;  //CH 
        4'b0110 : OUT = A6;  //DH 
        4'b0111 : OUT = A7;  //BH 
        4'b1000 : OUT = A8;  //AX 
        4'b1001 : OUT = A9;  //CX 
        4'b1010 : OUT = A10; //DX 
        4'b1011 : OUT = A11; //BX 
        4'b1100 : OUT = A12; //SP 
        4'b1101 : OUT = A13; //BP 
        4'b1110 : OUT = A14; //SI 
        4'b1111 : OUT = A15; //DI 
    endcase
end

endmodule

Proyecto 1/Reg16bits.v
//////////////////////////////////////////////////////////////////////////////////////////////////////
//
// Reg16bits.v
// 
// Este modulo sirve como para crear los registros de 16 bits
//
//////////////////////////////////////////////////////////////////////////////////////////////////////

module Reg16bits (
    input CLK, 
    input RST, 
    input WriteEnable,
    input [15:0] D,
    output reg [15:0] Q 
);
 
always @(posedge CLK or posedge RST) begin
    if (RST)
        Q = 16'b0;
    else if (WriteEnable)
        Q = D; 
    else 
        Q = Q;
end


endmodule

Proyecto 1/Reg8bits.v
//////////////////////////////////////////////////////////////////////////////////////////////////////
//
// Reg8bits.v
// 
// Este modulo sirve como registros de 8 bits
//
//////////////////////////////////////////////////////////////////////////////////////////////////////

module Reg8bits (
    input CLK, 
    input RST, 
    input WriteEnable,
    input [7:0] D,
    output reg [7:0] Q 
);
    

always @(posedge CLK or posedge RST) begin
    if (RST)
        Q = 8'b0;
    else if (WriteEnable)
        Q = D;
    else 
        Q = Q;
end

endmodule

Proyecto 1/Mux2x8.v
//////////////////////////////////////////////////////////////////////////////////////////////////////
//
// Mux2x8.v
// 
// Este modulo sirve como Mux2x8
//
//////////////////////////////////////////////////////////////////////////////////////////////////////

module Mux2x8 (
    input [7:0] ENT1,
    input [7:0] ENT2,
    input SEL_H_L,
    output reg [7:0] OUT
);

always @(*) begin
    case (SEL_H_L)
        1'b0 : OUT = ENT1;
        1'b1 : OUT = ENT2; 
    endcase
end

endmodule

Proyecto 1/Registros.v
//////////////////////////////////////////////////////////////////////////////////////////////////////
//
// Registros.v
// 
// Este modulo sirve como modulo para "crear" los registros
//
//////////////////////////////////////////////////////////////////////////////////////////////////////


module Registros (
    input CLK, 
    input RST, 
    input SEL,  
    input SEL_H_L,            
    input [15:0] DATA, 
    input [11:0] WE,

    output wire [7:0] AL, 
    output wire [7:0] CL, 
    output wire [7:0] DL, 
    output wire [7:0] BL, 
    output wire [7:0] AH, 
    output wire [7:0] CH, 
    output wire [7:0] DH, 
    output wire [7:0] BH,

    output wire [15:0] SP,  
    output wire [15:0] BP,
    output wire [15:0] SI,
    output wire [15:0] DI 
);

    
//Llamada al mux para selecionar High o Low en los registros de 8 bits
wire [7:0] Temp;
Mux2x8 mux2x8 (DATA[7:0], DATA [15:8], SEL_H_L, Temp);

//Llamada a Reg8bits para "crear" los registros de 8 bits
Reg8bits RegAL (CLK, RST, WE[11], DATA[7:0], AL); 
Reg8bits RegCL (CLK, RST, WE[10], DATA[7:0], CL); 
Reg8bits RegDL (CLK, RST, WE[9], DATA[7:0], DL); 
Reg8bits RegBL (CLK, RST, WE[8], DATA[7:0], BL); 
Reg8bits RegAH (CLK, RST, WE[7], Temp, AH); 
Reg8bits RegCH (CLK, RST, WE[6], Temp, CH); 
Reg8bits RegDH (CLK, RST, WE[5], Temp, DH); 
Reg8bits RegBH (CLK, RST, WE[4], Temp, BH); 

//Llamada a Reg16bits para "crear" los registros de 16 bits

Reg16bits RegSP (CLK, RST, WE[3], DATA, SP); 
Reg16bits RegBP (CLK, RST, WE[2], DATA, BP); 
Reg16bits RegSI (CLK, RST, WE[1], DATA, SI); 
Reg16bits RegDI (CLK, RST, WE[0], DATA, DI); 

endmodule

Proyecto 1/Deco.v
//////////////////////////////////////////////////////////////////////////////////////////////////////
//
// Deco.v
// 
// Este modulo sirve como Decodificador 
//
//////////////////////////////////////////////////////////////////////////////////////////////////////


module Deco (
    input WR,
    input [3:0] SEL, 
    output reg [11:0] WE
);
    
    always @(*) begin
        case ({WR, SEL})
            5'b10000 : WE = 12'b100000000000; //AL 
            5'b10001 : WE = 12'b010000000000; //CL
            5'b10010 : WE = 12'b001000000000; //DL
            5'b10011 : WE = 12'b001000000000; //BL
            5'b10100 : WE = 12'b000010000000; //AH
            5'b10101 : WE = 12'b000001000000; //CH
            5'b10110 : WE = 12'b100000100000; //DH
            5'b10111 : WE = 12'b100000010000; //BH
            5'b11000 : WE = 12'b100010000000; //AX
            5'b11001 : WE = 12'b010001000000; //CX
            5'b11010 : WE = 12'b001000100000; //DX
            5'b11011 : WE = 12'b000100010000; //BX
            5'b11100 : WE = 12'b000000001000; //SP
            5'b11101 : WE = 12'b000000000100; //BP
            5'b11110 : WE = 12'b000000000010; //SI
            5'b11111 : WE = 12'b000000000001; //DI

            default : WE = 12'b000000000000;  
        endcase
    end
endmodule

Proyecto 1/Top.v
//////////////////////////////////////////////////////////////////////////////////////////////////////
//
// Top.v
// 
// Este modulo sirve como Top para el banco de registros del 8088
//
//////////////////////////////////////////////////////////////////////////////////////////////////////

`include "Registros.v"
`include "Deco.v"
`include "Mux2x8.v"
`include "Mux16x1.v"
`include "Reg8bits.v"
`include "Reg16bits.v"
`include "TriS16bits.v"


module BancoDeRegistros8088 (
    input CLK, 
    input RST, 
    input RD, 
    input WR, 
    input [3:0] SEL, 
    inout wire [15:0] DATA
);

//Llamada al deco de escritura 
wire [11:0] WE;
Deco DecoEscritura (WR, SEL, WE);

wire SEL_H_L;
assign SEL_H_L = (
    SEL == 4'b0100 || SEL == 4'b0101 || SEL == 4'b0110 || SEL == 4'b0111 || // AH, CH, DH, BH
    SEL == 4'b1000 || SEL == 4'b1001 || SEL == 4'b1010 || SEL == 4'b1011    // AX, CX, DX, BX
);

//Llamada a Registros
wire [7:0] AL, CL, DL, BL, AH, CH, DH, BH;
wire [15:0] SP, BP, SI, DI;
Registros Regs (CLK, RST, SEL[3], SEL_H_L, DATA, WE, AL, CL, DL, BL, AH, CH, DH, BH, SP, BP, SI, DI);

//Llamada a mux16x1
wire [15:0] SALIDA;
Mux16x1 MuxSalida (
    {8'b0, AL},
    {8'b0, CL},
    {8'b0, DL},
    {8'b0, BL},
    {8'b0, AH},
    {8'b0, CH},
    {8'b0, DH},
    {8'b0, BH},
    {AH, AL},
    {CH, CL},
    {DH, DL},
    {BH, BL},
    SP, 
    BP, 
    SI, 
    DI,
    SEL, 
    SALIDA);


//Llamada al tri estado
    TriS16bits TriEstado (SALIDA, RD, DATA); 
    
endmodule

Proyecto 1/Top_tb_TESTERySCOREBOARD.sv
//////////////////////////////////////////////////////////////////////////////////////////////////////
//
// Top_tb_TESTERySCOREBOARD.sv
// 
// Este modulo sirve como testbench con teste y scoreboard del modulo top
//
//////////////////////////////////////////////////////////////////////////////////////////////////////


`timescale 1ns/1ns
`include "Top.v"

module Top_tb_TESTERySCOREBOARD ();

//Declaración de señales del testbench
bit CLK;
bit RST;
bit RD;
bit WR;
bit [3:0] SEL;

reg [15:0] dato_leido;

//Variables para el scoreboard
reg scoreboard_en;
reg [3:0] reg_leido;
reg [3:0] scoreboard_SEL;
reg [15:0] scoreboard_drive;
reg [15:0] scoreboard_dato_leido;
reg [15:0] expected [0:15];



integer i;
bit lectura = 0; //senal para determinar si scoreboard de lectura o escritura
bit escritura = 0;

// Contadores
integer ok_count_escritura = 0;
integer err_count_escritura = 0;
integer ok_count_lectura = 0;
integer err_count_lectura = 0;
integer repeticion = 0;


// Señales para controlar el bus inout
bit [15:0] DATA_drive;
bit DATA_en;
wire [15:0] DATA;


// Simulación del comportamiento triestado del bus
assign DATA = DATA_en ? DATA_drive : 16'bz;





//Instanciación del modulo BancoDeRegistros8088
BancoDeRegistros8088 DUT(
    .CLK(CLK),
    .RST(RST),
    .RD(RD),
    .WR(WR),
    .SEL(SEL),
    .DATA(DATA)
);



////////////////////////////////////////////////////////////////////////
//TESTER


//creacion del reloj
initial begin
    CLK = 0;
    forever #10 CLK =~ CLK;
end


//funcion para definir si leer o escribir 

function bit obtener_operacion_RD_WR();
    bit aleatorio;
    aleatorio = $urandom;    
    return aleatorio; //si retorna 1 es lectura, si no si retorna 0 es escritura
 
endfunction : obtener_operacion_RD_WR


function bit [15:0] obtener_valor();
    bit [2:0] ceros_y_unos;
    ceros_y_unos = $urandom;

    if (ceros_y_unos == 3'b000)
        return 16'h0000;
    
    else if (ceros_y_unos == 3'b111)
        return 16'hFFFF;
    else
        return $urandom;
    
endfunction : obtener_valor


function bit [3:0] obtener_registro();
    return $urandom;
endfunction





//inicio de tester

    initial begin : tester


        $dumpfile("Top_tb_TESTERySCOREBOARD.vcd");
        $dumpvars(0, Top_tb_TESTERySCOREBOARD);
      
        // Reset inicial
        @(posedge CLK); RST = 1; WR = 0; RD = 0; SEL = 0;
                    DATA_drive = 16'h0000;
                    DATA_en = 0;
        #20 

        @(posedge CLK); 
        @(posedge CLK);
        RST = 0;
 
        for (i = 0; i < 16; i++) begin
            expected[i] = 16'h0000;
        end

//testing//////////////////////////////////////////////////////////////////////////////
        repeat (20) begin

            @(posedge CLK);
            
            repeticion++;

            //obtener operacion: lectura = 1 | escritura = 0
            RD = obtener_operacion_RD_WR();

            $display("Repeticion: %0d", repeticion);
            //$display(""); // Línea en blanco


            if (RD == 1) begin     //Lectura de registro
                lectura = 1;

                $display("Valor de RD: %b (LECTURA DE REGISTROS)", RD);
                SEL = obtener_registro();
                DATA_en = 0;
                WR = 0;


                #20;
                
                
                DATA_en = 1;
                dato_leido = DATA;
                
                $display("Leyendo registro %0d, dato_leido = %h", SEL, dato_leido);
                $display("Leyendo registro %0d, expected[SEL] = %h", SEL, expected[SEL]);
                $display(" ");

                RD = 0;
                DATA_en = 0;
                scoreboard_SEL = SEL;
                scoreboard_drive = DATA_drive;
                scoreboard_dato_leido = dato_leido;
                reg_leido = SEL;
                scoreboard_en = 1;
            end 



            else begin             //Escritura en registro
                #20;
                escritura = 1;
                $display("Valor de RD: %b (ESCRITURA DE REGISTROS)", RD);

                SEL = obtener_registro();
                DATA_drive = obtener_valor();
                DATA_en = 1;
                WR = 1;
                
                
                
                #30;
                
                
                WR = 0;
                DATA_en = 0;

                
                $display("Escribiendo %h en registro %0d", DATA_drive, SEL);


                
                
                RD = 1;


                #20;


                DATA_en = 1;
                dato_leido = DATA;
                
                
                $display("Lectura desde reg %0d: %h", SEL, dato_leido);
                $display(""); // Línea en blanco

                scoreboard_SEL = SEL;
                scoreboard_drive = DATA_drive;
                scoreboard_dato_leido = dato_leido;
                reg_leido = SEL;
                expected[SEL] = scoreboard_dato_leido;


                RD = 0;
                #20
                scoreboard_en = 1;
                

            end

        end



        $display("Tester terminado.");
        $display("Resumen final:");

        $display("Escrituras Totales Correctas: %0d", ok_count_escritura);
        $display("Escrituras Totales Erroneas: %0d", err_count_escritura);

        $display("Lecturas Totales Correctos: %0d", ok_count_lectura);
        $display("Lecturas Totales Erroneas: %0d", err_count_lectura);
        $finish; 
    end : tester



//SCOREBOARD
    always @(scoreboard_en) begin : scoreboard
        if (scoreboard_en) begin
            scoreboard_en = 0; // desactiva para siguiente ciclo

            if (escritura == 1) begin
                $display("Valor de SEL: %b:", scoreboard_SEL);
                $display("Valor de DATA_drive: %h:", scoreboard_drive);
                $display("Valor de dato_leido: %h:", scoreboard_dato_leido);
                escritura = 0; 
            
                if (scoreboard_SEL[3:2] == 2'b00) begin      //registros de 8 bits lows
                    
                    if (scoreboard_drive [7:0] == scoreboard_dato_leido[7:0]) begin
                        $display("SCOREBOARD escritura OK: REG = %0d | Dato de entrada = %h | Leido = %h", reg_leido, scoreboard_drive, scoreboard_dato_leido);
                        $display(""); // Línea en blanco
                        ok_count_escritura++;
                    end 

                    else begin
                        $display("SCOREBOARD escritura ERROR: REG = %0d | Esperado = %h | Leido = %h", reg_leido, scoreboard_drive, scoreboard_dato_leido);
                        $display(""); // Línea en blanco
                        err_count_escritura++;
                    end 
                end 

                else if (SEL[3:2] == 2'b01) begin

                        if (scoreboard_drive [15:8] == scoreboard_dato_leido[7:0]) begin
                            $display("SCOREBOARD escritura OK: REG = %0d | Dato de entrada = %h | Leido = %h", reg_leido, scoreboard_drive, scoreboard_dato_leido);
                            $display(""); // Línea en blanco
                            ok_count_escritura++;
                        end 

                        else begin
                            $display("SCOREBOARD escritura ERROR: REG = %0d | Esperado = %h | Leido = %h", reg_leido, scoreboard_drive, scoreboard_dato_leido);
                            $display(""); // Línea en blanco
                            err_count_escritura++;
                        end 
                    end

                else begin
                    if (scoreboard_drive == scoreboard_dato_leido) begin
                            $display("SCOREBOARD escritura OK: REG = %0d | Dato de entrada = %h | Leido = %h", reg_leido, scoreboard_drive, scoreboard_dato_leido);
                            $display(""); // Línea en blanco
                            ok_count_escritura++;
                    end
                    else begin
                            $display("SCOREBOARD escritura ERROR: REG = %0d | Esperado = %h | Leido = %h", reg_leido, scoreboard_drive, scoreboard_dato_leido);
                            $display(""); // Línea en blanco
                            err_count_escritura++;
                    end
                end
            end


            else if (lectura == 1) begin
                    lectura = 0;
                    if (expected[SEL] == dato_leido) begin
                        $display("SCOREBOARD lectura OK: REG = %0d | Dato Leido = %h | Dato esperado = %h", reg_leido, dato_leido, expected[SEL]);
                        $display(""); // Línea en blanco
                        ok_count_lectura++;
                    end
                    else begin
                        $display("SCOREBOARD lectura ERROR: REG = %0d | Dato Leido = %h | Dato esperado = %h", reg_leido, dato_leido, expected[SEL]);
                        $display(""); // Línea en blanco
                        err_count_lectura++;
                    end
                end
            end
 
    end : scoreboard




endmodule

Proyecto 1/Top_tb_TESTERySCOREBOARD.vcd
$date
	Thu Apr 17 17:32:35 2025
$end
$version
	Icarus Verilog
$end
$timescale
	1ns
$end
$scope module Top_tb_TESTERySCOREBOARD $end
$var wire 16 ! DATA [15:0] $end
$var reg 16 " dato_leido [15:0] $end
$var reg 4 # reg_leido [3:0] $end
$var reg 4 $ scoreboard_SEL [3:0] $end
$var reg 16 % scoreboard_dato_leido [15:0] $end
$var reg 16 & scoreboard_drive [15:0] $end
$var reg 1 ' scoreboard_en $end
$var reg 1 ( CLK $end
$var reg 16 ) DATA_drive [15:0] $end
$var reg 1 * DATA_en $end
$var reg 1 + RD $end
$var reg 1 , RST $end
$var reg 4 - SEL [3:0] $end
$var reg 1 . WR $end
$var integer 32 / err_count_escritura [31:0] $end
$var integer 32 0 err_count_lectura [31:0] $end
$var reg 1 1 escritura $end
$var integer 32 2 i [31:0] $end
$var reg 1 3 lectura $end
$var integer 32 4 ok_count_escritura [31:0] $end
$var integer 32 5 ok_count_lectura [31:0] $end
$var integer 32 6 repeticion [31:0] $end
$scope function obtener_operacion_RD_WR $end
$var reg 1 7 aleatorio $end
$upscope $end
$scope function obtener_registro $end
$upscope $end
$scope function obtener_valor $end
$var reg 3 8 ceros_y_unos [2:0] $end
$upscope $end
$scope module DUT $end
$var wire 1 ( CLK $end
$var wire 16 9 DATA [15:0] $end
$var wire 1 + RD $end
$var wire 1 , RST $end
$var wire 4 : SEL [3:0] $end
$var wire 1 ; SEL_H_L $end
$var wire 1 . WR $end
$var wire 12 < WE [11:0] $end
$var wire 16 = SP [15:0] $end
$var wire 16 > SI [15:0] $end
$var wire 16 ? SALIDA [15:0] $end
$var wire 8 @ DL [7:0] $end
$var wire 16 A DI [15:0] $end
$var wire 8 B DH [7:0] $end
$var wire 8 C CL [7:0] $end
$var wire 8 D CH [7:0] $end
$var wire 16 E BP [15:0] $end
$var wire 8 F BL [7:0] $end
$var wire 8 G BH [7:0] $end
$var wire 8 H AL [7:0] $end
$var wire 8 I AH [7:0] $end
$scope module DecoEscritura $end
$var wire 4 J SEL [3:0] $end
$var wire 1 . WR $end
$var reg 12 K WE [11:0] $end
$upscope $end
$scope module MuxSalida $end
$var wire 16 L A0 [15:0] $end
$var wire 16 M A1 [15:0] $end
$var wire 16 N A10 [15:0] $end
$var wire 16 O A11 [15:0] $end
$var wire 16 P A2 [15:0] $end
$var wire 16 Q A3 [15:0] $end
$var wire 16 R A4 [15:0] $end
$var wire 16 S A5 [15:0] $end
$var wire 16 T A6 [15:0] $end
$var wire 16 U A7 [15:0] $end
$var wire 16 V A8 [15:0] $end
$var wire 16 W A9 [15:0] $end
$var wire 4 X SEL [3:0] $end
$var wire 16 Y A15 [15:0] $end
$var wire 16 Z A14 [15:0] $end
$var wire 16 [ A13 [15:0] $end
$var wire 16 \ A12 [15:0] $end
$var reg 16 ] OUT [15:0] $end
$upscope $end
$scope module Regs $end
$var wire 1 ( CLK $end
$var wire 16 ^ DATA [15:0] $end
$var wire 1 , RST $end
$var wire 1 _ SEL $end
$var wire 1 ; SEL_H_L $end
$var wire 12 ` WE [11:0] $end
$var wire 8 a Temp [7:0] $end
$var wire 16 b SP [15:0] $end
$var wire 16 c SI [15:0] $end
$var wire 8 d DL [7:0] $end
$var wire 16 e DI [15:0] $end
$var wire 8 f DH [7:0] $end
$var wire 8 g CL [7:0] $end
$var wire 8 h CH [7:0] $end
$var wire 16 i BP [15:0] $end
$var wire 8 j BL [7:0] $end
$var wire 8 k BH [7:0] $end
$var wire 8 l AL [7:0] $end
$var wire 8 m AH [7:0] $end
$scope module RegAH $end
$var wire 1 ( CLK $end
$var wire 1 , RST $end
$var wire 1 n WriteEnable $end
$var wire 8 o D [7:0] $end
$var reg 8 p Q [7:0] $end
$upscope $end
$scope module RegAL $end
$var wire 1 ( CLK $end
$var wire 8 q D [7:0] $end
$var wire 1 , RST $end
$var wire 1 r WriteEnable $end
$var reg 8 s Q [7:0] $end
$upscope $end
$scope module RegBH $end
$var wire 1 ( CLK $end
$var wire 1 , RST $end
$var wire 1 t WriteEnable $end
$var wire 8 u D [7:0] $end
$var reg 8 v Q [7:0] $end
$upscope $end
$scope module RegBL $end
$var wire 1 ( CLK $end
$var wire 8 w D [7:0] $end
$var wire 1 , RST $end
$var wire 1 x WriteEnable $end
$var reg 8 y Q [7:0] $end
$upscope $end
$scope module RegBP $end
$var wire 1 ( CLK $end
$var wire 16 z D [15:0] $end
$var wire 1 , RST $end
$var wire 1 { WriteEnable $end
$var reg 16 | Q [15:0] $end
$upscope $end
$scope module RegCH $end
$var wire 1 ( CLK $end
$var wire 1 , RST $end
$var wire 1 } WriteEnable $end
$var wire 8 ~ D [7:0] $end
$var reg 8 !" Q [7:0] $end
$upscope $end
$scope module RegCL $end
$var wire 1 ( CLK $end
$var wire 8 "" D [7:0] $end
$var wire 1 , RST $end
$var wire 1 #" WriteEnable $end
$var reg 8 $" Q [7:0] $end
$upscope $end
$scope module RegDH $end
$var wire 1 ( CLK $end
$var wire 1 , RST $end
$var wire 1 %" WriteEnable $end
$var wire 8 &" D [7:0] $end
$var reg 8 '" Q [7:0] $end
$upscope $end
$scope module RegDI $end
$var wire 1 ( CLK $end
$var wire 16 (" D [15:0] $end
$var wire 1 , RST $end
$var wire 1 )" WriteEnable $end
$var reg 16 *" Q [15:0] $end
$upscope $end
$scope module RegDL $end
$var wire 1 ( CLK $end
$var wire 8 +" D [7:0] $end
$var wire 1 , RST $end
$var wire 1 ," WriteEnable $end
$var reg 8 -" Q [7:0] $end
$upscope $end
$scope module RegSI $end
$var wire 1 ( CLK $end
$var wire 16 ." D [15:0] $end
$var wire 1 , RST $end
$var wire 1 /" WriteEnable $end
$var reg 16 0" Q [15:0] $end
$upscope $end
$scope module RegSP $end
$var wire 1 ( CLK $end
$var wire 16 1" D [15:0] $end
$var wire 1 , RST $end
$var wire 1 2" WriteEnable $end
$var reg 16 3" Q [15:0] $end
$upscope $end
$scope module mux2x8 $end
$var wire 8 4" ENT1 [7:0] $end
$var wire 8 5" ENT2 [7:0] $end
$var wire 1 ; SEL_H_L $end
$var reg 8 6" OUT [7:0] $end
$upscope $end
$upscope $end
$scope module TriEstado $end
$var wire 16 7" IN [15:0] $end
$var wire 16 8" OUT [15:0] $end
$var wire 1 + SEL $end
$upscope $end
$upscope $end
$scope begin scoreboard $end
$upscope $end
$scope begin tester $end
$upscope $end
$upscope $end
$enddefinitions $end
$comment Show the parameter values. $end
$dumpall
$end
#0
$dumpvars
bz 8"
b0xxxxxxxx 7"
bz 6"
bz 5"
bz 4"
bx 3"
x2"
bz 1"
bx 0"
x/"
bz ."
bx -"
x,"
bz +"
bx *"
x)"
bz ("
bx '"
bz &"
x%"
bx $"
x#"
bz ""
bx !"
bz ~
x}
bx |
x{
bz z
bx y
xx
bz w
bx v
bz u
xt
bx s
xr
bz q
bx p
bz o
xn
bx m
bx l
bx k
bx j
bx i
bx h
bx g
bx f
bx e
bx d
bx c
bx b
bz a
bx `
0_
bz ^
b0xxxxxxxx ]
bx \
bx [
bx Z
bx Y
b0 X
bx W
bx V
b0xxxxxxxx U
b0xxxxxxxx T
b0xxxxxxxx S
b0xxxxxxxx R
b0xxxxxxxx Q
b0xxxxxxxx P
bx O
bx N
b0xxxxxxxx M
b0xxxxxxxx L
bx K
b0 J
bx I
bx H
bx G
bx F
bx E
bx D
bx C
bx B
bx A
bx @
b0xxxxxxxx ?
bx >
bx =
bx <
0;
b0 :
bz 9
b0 8
07
b0 6
b0 5
b0 4
03
bx 2
01
b0 0
b0 /
0.
b0 -
0,
0+
0*
b0 )
0(
x'
bx &
bx %
bx $
bx #
bx "
bz !
$end
#10
b0 =
b0 \
b0 b
b0 3"
b0 E
b0 [
b0 i
b0 |
b0 >
b0 Z
b0 c
b0 0"
b0 A
b0 Y
b0 e
b0 *"
b0 ?
b0 ]
b0 7"
b0 L
b0 H
b0 l
b0 s
b0 M
b0 C
b0 g
b0 $"
b0 P
b0 @
b0 d
b0 -"
b0 Q
b0 F
b0 j
b0 y
b0 V
b0 R
b0 I
b0 m
b0 p
b0 W
b0 S
b0 D
b0 h
b0 !"
b0 N
b0 T
b0 B
b0 f
b0 '"
b0 O
b0 U
b0 G
b0 k
b0 v
1,
1(
#20
0(
#30
1(
#40
0(
#50
b10000 2
0,
1(
#60
0(
#70
b1 6
1(
#80
0(
#90
b1100011 a
b1100011 o
b1100011 u
b1100011 ~
b1100011 &"
b1100011 6"
b1100011 4"
b1010110 5"
b1100011 q
b1100011 ""
b1100011 +"
b1100011 w
0r
1#"
0,"
0x
0n
0}
0%"
0t
02"
0{
0/"
0)"
b101011001100011 !
b101011001100011 9
b101011001100011 ^
b101011001100011 z
b101011001100011 ("
b101011001100011 ."
b101011001100011 1"
b101011001100011 8"
b10000000000 <
b10000000000 K
b10000000000 `
1(
1.
1*
b101011001100011 )
b1 8
b1 -
b1 :
b1 J
b1 X
11
#100
0(
#110
b1100011 ?
b1100011 ]
b1100011 7"
b1100011 W
b1100011 M
b1100011 C
b1100011 g
b1100011 $"
1(
#120
b0 5"
0#"
b1100011 !
b1100011 9
b1100011 ^
b1100011 z
b1100011 ("
b1100011 ."
b1100011 1"
b1100011 8"
b0 <
b0 K
b0 `
0(
1+
0*
0.
#130
1(
#140
b1010110 5"
b101011001100011 !
b101011001100011 9
b101011001100011 ^
b101011001100011 z
b101011001100011 ("
b101011001100011 ."
b101011001100011 1"
b101011001100011 8"
0(
0+
b1 #
b1100011 %
b101011001100011 &
b1 $
b1100011 "
1*
#150
1(
#160
b1 4
01
0(
0'
#170
b0 a
b0 o
b0 u
b0 ~
b0 &"
b0 6"
b0 4"
b0 q
b0 ""
b0 +"
b0 w
b0 5"
1_
b0 ?
b0 ]
b0 7"
b0 !
b0 9
b0 ^
b0 z
b0 ("
b0 ."
b0 1"
b0 8"
0*
b1101 -
b1101 :
b1101 J
b1101 X
13
1+
17
b10 6
1(
#180
0(
#190
b0 a
b0 o
b0 u
b0 ~
b0 &"
b0 6"
0_
b0 4"
b0 5"
b0 q
b0 ""
b0 +"
b0 w
b10 -
b10 :
b10 J
b10 X
b11 6
b1 5
13
b0 !
b0 9
b0 ^
b0 z
b0 ("
b0 ."
b0 1"
b0 8"
1(
0'
b1101 #
b0 %
b1101 $
1+
b0 "
0*
#200
0(
#210
b0 a
b0 o
b0 u
b0 ~
b0 &"
b0 6"
1_
b0 4"
b0 5"
b0 q
b0 ""
b0 +"
b0 w
b1101 -
b1101 :
b1101 J
b1101 X
b100 6
b10 5
13
b0 !
b0 9
b0 ^
b0 z
b0 ("
b0 ."
b0 1"
b0 8"
1(
0'
b10 #
b10 $
1+
0*
#220
0(
#230
bz a
bz o
bz u
bz ~
bz &"
bz 6"
bz 4"
bz 5"
bz q
bz ""
bz +"
bz w
07
b101 6
b11 5
03
bz !
bz 9
bz ^
bz z
bz ("
bz ."
bz 1"
bz 8"
1(
0'
b1101 #
b1101 $
0+
0*
#240
0(
#250
b10001100 a
b10001100 o
b10001100 u
b10001100 ~
b10001100 &"
b10001100 6"
1{
b10001100 4"
b11110111 5"
b10001100 q
b10001100 ""
b10001100 +"
b10001100 w
b100 <
b100 K
b100 `
b1111011110001100 !
b1111011110001100 9
b1111011110001100 ^
b1111011110001100 z
b1111011110001100 ("
b1111011110001100 ."
b1111011110001100 1"
b1111011110001100 8"
1(
1.
1*
b1111011110001100 )
b101 8
11
#260
0(
#270
b1111011110001100 ?
b1111011110001100 ]
b1111011110001100 7"
b1111011110001100 E
b1111011110001100 [
b1111011110001100 i
b1111011110001100 |
1(
#280
0{
b1111011110001100 !
b1111011110001100 9
b1111011110001100 ^
b1111011110001100 z
b1111011110001100 ("
b1111011110001100 ."
b1111011110001100 1"
b1111011110001100 8"
b0 <
b0 K
b0 `
0(
1+
0*
0.
#290
1(
#300
0(
0+
b1111011110001100 %
b1111011110001100 &
b1111011110001100 "
1*
#310
1(
#320
b10 4
01
0(
0'
#330
1;
b0 a
b0 o
b0 u
b0 ~
b0 &"
b0 6"
b0 4"
b0 5"
b0 q
b0 ""
b0 +"
b0 w
b0 !
b0 9
b0 ^
b0 z
b0 ("
b0 ."
b0 1"
b0 8"
0_
b0 ?
b0 ]
b0 7"
0*
b110 -
b110 :
b110 J
b110 X
13
1+
17
b110 6
1(
#340
0(
#350
b0 a
b0 o
b0 u
b0 ~
b0 &"
b0 6"
1_
b0 4"
b0 5"
b0 q
b0 ""
b0 +"
b0 w
b1010 -
b1010 :
b1010 J
b1010 X
b111 6
b100 5
13
b0 !
b0 9
b0 ^
b0 z
b0 ("
b0 ."
b0 1"
b0 8"
1(
0'
b110 #
b0 %
b110 $
1+
b0 "
0*
#360
0(
#370
1;
b0 a
b0 o
b0 u
b0 ~
b0 &"
b0 6"
0_
b0 4"
b0 5"
b0 q
b0 ""
b0 +"
b0 w
b111 -
b111 :
b111 J
b111 X
b1000 6
b101 5
13
b0 !
b0 9
b0 ^
b0 z
b0 ("
b0 ."
b0 1"
b0 8"
1(
0'
b1010 #
b1010 $
1+
0*
#380
0(
#390
bz a
bz o
bz u
bz ~
bz &"
bz 6"
bz 4"
bz 5"
bz q
bz ""
bz +"
bz w
07
b1001 6
b110 5
03
bz !
bz 9
bz ^
bz z
bz ("
bz ."
bz 1"
bz 8"
1(
0'
b111 #
b111 $
0+
0*
#400
0(
#410
0;
b11001110 a
b11001110 o
b11001110 u
b11001110 ~
b11001110 &"
b11001110 6"
b11001110 4"
b10010110 5"
b11001110 q
b11001110 ""
b11001110 +"
b11001110 w
1)"
b1001011011001110 !
b1001011011001110 9
b1001011011001110 ^
b1001011011001110 z
b1001011011001110 ("
b1001011011001110 ."
b1001011011001110 1"
b1001011011001110 8"
1_
b1 <
b1 K
b1 `
1(
1.
1*
b1001011011001110 )
b10 8
b1111 -
b1111 :
b1111 J
b1111 X
11
#420
0(
#430
b1001011011001110 ?
b1001011011001110 ]
b1001011011001110 7"
b1001011011001110 A
b1001011011001110 Y
b1001011011001110 e
b1001011011001110 *"
1(
#440
0)"
b1001011011001110 !
b1001011011001110 9
b1001011011001110 ^
b1001011011001110 z
b1001011011001110 ("
b1001011011001110 ."
b1001011011001110 1"
b1001011011001110 8"
b0 <
b0 K
b0 `
0(
1+
0*
0.
#450
1(
#460
0(
0+
b1111 #
b1001011011001110 %
b1001011011001110 &
b1111 $
b1001011011001110 "
1*
#470
1(
#480
b11 4
01
0(
0'
#490
b1010 6
1(
#500
0(
